lixiang90sblog/__init__.py
lixiang90sblog/blog.py
lixiang90sblog/client.py
lixiang90sblog/blog/0.txt
lixiang90sblog/blog/1.txt
lixiang90sblog/blog/2.txt
lixiang90sblog/blog/metadata.json
lixiang90sblog-0.1.1.dist-info/METADATA
lixiang90sblog-0.1.1.dist-info/WHEEL
lixiang90sblog-0.1.1.dist-info/top_level.txt
lixiang90sblog-0.1.1.dist-info/RECORD
