Metadata-Version: 2.1
Name: lixiang90sblog
Version: 0.1.1
Summary: Lixiang90's personal blog
Home-page: https://github.com/lixiang90/lixiang90sblog.git
Author: lixiang90
Author-email: lixiang90@github.com
Classifier: Programming Language :: Python :: 3
Classifier: License :: OSI Approved :: MIT License
Classifier: Operating System :: OS Independent
Requires-Python: >=3.7
